{
  "gitSyncId": "6841cb726a626865613a3b7b_6ee30012-ec99-4a6d-bd7a-780ee86855aa",
  "id": "Recetas dashboard V3_insert_ingrediente",
  "pluginId": "postgres-plugin",
  "pluginType": "DB",
  "unpublishedAction": {
    "actionConfiguration": {
      "body": "INSERT INTO ingredientes\n  (nombre, unidad_base_id, kcal_100, prot_100, grasa_100, carb_100, fibra_100)\nVALUES\n  ('{{ input_new_ing_nombre.text }}',\n   '{{ select_new_unidad_base.selectedOptionValue }}',\n   {{ kcal_100 }},\n   {{ prot_100 }},\n   {{ grasa_100 }},\n   {{ carb_100 }},\n   {{ fibra_100 }});\n",
      "encodeParamsToggle": true,
      "paginationType": "NONE",
      "pluginSpecifiedTemplates": [
        {
          "value": true
        }
      ],
      "timeoutInMillisecond": 10000
    },
    "confirmBeforeExecute": false,
    "datasource": {
      "id": "Supabase_ComidaSimple",
      "isAutoGenerated": false,
      "name": "Supabase_ComidaSimple",
      "pluginId": "postgres-plugin"
    },
    "dynamicBindingPathList": [
      {
        "key": "body"
      }
    ],
    "name": "insert_ingrediente",
    "pageId": "Recetas dashboard V3",
    "runBehaviour": "MANUAL",
    "userSetOnLoad": false
  }
}